fullctl/__init__.py
fullctl/django/__init__.py
fullctl/django/admin.py
fullctl/django/apps.py
fullctl/django/auditlog.py
fullctl/django/auth.py
fullctl/django/autocomplete/__init__.py
fullctl/django/autocomplete/devicectl.py
fullctl/django/autocomplete/pdb.py
fullctl/django/autocomplete/prefixctl.py
fullctl/django/context.py
fullctl/django/context_processors.py
fullctl/django/decorators.py
fullctl/django/enum.py
fullctl/django/exceptions.py
fullctl/django/fields/__init__.py
fullctl/django/fields/service_bridge/__init__.py
fullctl/django/fields/service_bridge/prefixctl.py
fullctl/django/forms.py
fullctl/django/health_check.py
fullctl/django/inet/__init__.py
fullctl/django/inet/const.py
fullctl/django/inet/exceptions.py
fullctl/django/inet/fields.py
fullctl/django/inet/util.py
fullctl/django/inet/validators.py
fullctl/django/mail.py
fullctl/django/management/__init__.py
fullctl/django/management/commands/__init__.py
fullctl/django/management/commands/base.py
fullctl/django/management/commands/fullctl_local_setup.py
fullctl/django/management/commands/fullctl_manage_tasks.py
fullctl/django/management/commands/fullctl_poll_tasks.py
fullctl/django/management/commands/fullctl_promote_user.py
fullctl/django/management/commands/fullctl_work_task.py
fullctl/django/middleware.py
fullctl/django/migrations/0001_initial.py
fullctl/django/migrations/0002_delete_apikey.py
fullctl/django/migrations/0003_auditlog.py
fullctl/django/migrations/0004_auto_20210528_1247.py
fullctl/django/migrations/0005_auto_20210528_1252.py
fullctl/django/migrations/0006_auto_20210603_0542.py
fullctl/django/migrations/0007_auditlog_ip_address.py
fullctl/django/migrations/0008_managementtask.py
fullctl/django/migrations/0009_taskclaim.py
fullctl/django/migrations/0010_alter_managementtask_queue_id.py
fullctl/django/migrations/0011_alter_managementtask_status.py
fullctl/django/migrations/0012_auto_20210805_1153.py
fullctl/django/migrations/0013_auto_20210805_1200.py
fullctl-1.14.0.dist-info/LICENSE
fullctl-1.14.0.dist-info/METADATA
fullctl-1.14.0.dist-info/WHEEL
fullctl-1.14.0.dist-info/entry_points.txt
fullctl-1.14.0.dist-info/RECORD
