Metadata-Version: 2.1
Name: fullctl
Version: 1.14.0
Summary: Core classes and functions for service applications
Home-page: https://github.com/fullctl/fullctl
License: Apache-2.0
Author: FullCtl
Author-email: code@fullctl.com
Requires-Python: >=3.9,<4.0
Classifier: Development Status :: 5 - Production/Stable
Classifier: Intended Audience :: Developers
Classifier: License :: OSI Approved :: Apache Software License
Classifier: Programming Language :: Python :: 3
Classifier: Programming Language :: Python :: 3.9
Classifier: Programming Language :: Python :: 3.10
Classifier: Programming Language :: Python :: 3.11
Classifier: Programming Language :: Python :: 3.12
Classifier: Topic :: Software Development
Requires-Dist: confu (>=1.9)
Requires-Dist: django (>=3.2)
Requires-Dist: django-autocomplete-light (>=3.9.7)
Requires-Dist: django-cors-headers (>=4.3.1)
Requires-Dist: django-countries (>=7.6)
Requires-Dist: django-crispy-forms (>=2.0)
Requires-Dist: django-filter (>=23.4)
Requires-Dist: django-grainy (>=2)
Requires-Dist: django-handleref (>=2)
Requires-Dist: django-inet (>=1)
Requires-Dist: django-netfields (<2)
Requires-Dist: django-recaptcha (>=2)
Requires-Dist: django-reversion (>=5)
Requires-Dist: django-structlog (>=2.1.3)
Requires-Dist: djangorestframework (>=3)
Requires-Dist: grainy (>=1.8.1)
Requires-Dist: munge (>=1.3.0)
Requires-Dist: psycopg[binary] (>=3.1.8)
Requires-Dist: pydantic (>=2.6.3)
Requires-Dist: pyuwsgi (>=2.0.19)
Requires-Dist: pyyaml (>=5)
Requires-Dist: setuptools
Requires-Dist: social-auth-app-django (>=5.2)
Requires-Dist: whitenoise (>=6)
Project-URL: Repository, https://github.com/fullctl/fullctl
